<?xml version="1.0" standalone="yes"?>
<xs:schema id="eTaxBillDS" xmlns="" xmlns:xs="http://www.w3.org/2001/XMLSchema" xmlns:msdata="urn:schemas-microsoft-com:xml-msdata">
  <xs:element name="eTaxBillDS" msdata:IsDataSet="true" msdata:UseCurrentLocale="true">
    <xs:complexType>
      <xs:choice minOccurs="0" maxOccurs="unbounded">
        <xs:element name="TB_eTAX_INVOICE">
          <xs:complexType>
            <xs:sequence>
              <xs:element name="exchangeId">
                <xs:simpleType>
                  <xs:restriction base="xs:string">
                    <xs:maxLength value="24" />
                  </xs:restriction>
                </xs:simpleType>
              </xs:element>
              <xs:element name="exchangeDate" type="xs:dateTime" />
              <xs:element name="isIssued">
                <xs:simpleType>
                  <xs:restriction base="xs:string">
                    <xs:maxLength value="1" />
                  </xs:restriction>
                </xs:simpleType>
              </xs:element>
              <xs:element name="isSuccess">
                <xs:simpleType>
                  <xs:restriction base="xs:string">
                    <xs:maxLength value="1" />
                  </xs:restriction>
                </xs:simpleType>
              </xs:element>
              <xs:element name="refIssueId" minOccurs="0">
                <xs:simpleType>
                  <xs:restriction base="xs:string">
                    <xs:maxLength value="24" />
                  </xs:restriction>
                </xs:simpleType>
              </xs:element>
              <xs:element name="creator" minOccurs="0">
                <xs:simpleType>
                  <xs:restriction base="xs:string">
                    <xs:maxLength value="30" />
                  </xs:restriction>
                </xs:simpleType>
              </xs:element>
              <xs:element name="issueId">
                <xs:simpleType>
                  <xs:restriction base="xs:string">
                    <xs:maxLength value="24" />
                  </xs:restriction>
                </xs:simpleType>
              </xs:element>
              <xs:element name="issueDate" type="xs:dateTime" />
              <xs:element name="typeCode">
                <xs:simpleType>
                  <xs:restriction base="xs:string">
                    <xs:maxLength value="4" />
                  </xs:restriction>
                </xs:simpleType>
              </xs:element>
              <xs:element name="purposeCode" minOccurs="0">
                <xs:simpleType>
                  <xs:restriction base="xs:string">
                    <xs:maxLength value="2" />
                  </xs:restriction>
                </xs:simpleType>
              </xs:element>
              <xs:element name="amendmentCode" minOccurs="0">
                <xs:simpleType>
                  <xs:restriction base="xs:string">
                    <xs:maxLength value="2" />
                  </xs:restriction>
                </xs:simpleType>
              </xs:element>
              <xs:element name="description" minOccurs="0">
                <xs:simpleType>
                  <xs:restriction base="xs:string">
                    <xs:maxLength value="150" />
                  </xs:restriction>
                </xs:simpleType>
              </xs:element>
              <xs:element name="importId" minOccurs="0">
                <xs:simpleType>
                  <xs:restriction base="xs:string">
                    <xs:maxLength value="15" />
                  </xs:restriction>
                </xs:simpleType>
              </xs:element>
              <xs:element name="importStart" type="xs:dateTime" minOccurs="0" />
              <xs:element name="importEnd" type="xs:dateTime" minOccurs="0" />
              <xs:element name="importQuantity" type="xs:decimal" />
              <xs:element name="invoicerId">
                <xs:simpleType>
                  <xs:restriction base="xs:string">
                    <xs:maxLength value="13" />
                  </xs:restriction>
                </xs:simpleType>
              </xs:element>
              <xs:element name="invoicerOrgId" minOccurs="0">
                <xs:simpleType>
                  <xs:restriction base="xs:string">
                    <xs:maxLength value="4" />
                  </xs:restriction>
                </xs:simpleType>
              </xs:element>
              <xs:element name="invoicerName">
                <xs:simpleType>
                  <xs:restriction base="xs:string">
                    <xs:maxLength value="70" />
                  </xs:restriction>
                </xs:simpleType>
              </xs:element>
              <xs:element name="invoicerPerson">
                <xs:simpleType>
                  <xs:restriction base="xs:string">
                    <xs:maxLength value="30" />
                  </xs:restriction>
                </xs:simpleType>
              </xs:element>
              <xs:element name="invoicerAddress" minOccurs="0">
                <xs:simpleType>
                  <xs:restriction base="xs:string">
                    <xs:maxLength value="150" />
                  </xs:restriction>
                </xs:simpleType>
              </xs:element>
              <xs:element name="invoicerType" minOccurs="0">
                <xs:simpleType>
                  <xs:restriction base="xs:string">
                    <xs:maxLength value="40" />
                  </xs:restriction>
                </xs:simpleType>
              </xs:element>
              <xs:element name="invoicerClass" minOccurs="0">
                <xs:simpleType>
                  <xs:restriction base="xs:string">
                    <xs:maxLength value="40" />
                  </xs:restriction>
                </xs:simpleType>
              </xs:element>
              <xs:element name="invoicerDepartment" minOccurs="0">
                <xs:simpleType>
                  <xs:restriction base="xs:string">
                    <xs:maxLength value="40" />
                  </xs:restriction>
                </xs:simpleType>
              </xs:element>
              <xs:element name="invoicerContactor" minOccurs="0">
                <xs:simpleType>
                  <xs:restriction base="xs:string">
                    <xs:maxLength value="30" />
                  </xs:restriction>
                </xs:simpleType>
              </xs:element>
              <xs:element name="invoicerPhone" minOccurs="0">
                <xs:simpleType>
                  <xs:restriction base="xs:string">
                    <xs:maxLength value="20" />
                  </xs:restriction>
                </xs:simpleType>
              </xs:element>
              <xs:element name="invoicerEMail" minOccurs="0">
                <xs:simpleType>
                  <xs:restriction base="xs:string">
                    <xs:maxLength value="40" />
                  </xs:restriction>
                </xs:simpleType>
              </xs:element>
              <xs:element name="invoiceeId">
                <xs:simpleType>
                  <xs:restriction base="xs:string">
                    <xs:maxLength value="13" />
                  </xs:restriction>
                </xs:simpleType>
              </xs:element>
              <xs:element name="invoiceeKind">
                <xs:simpleType>
                  <xs:restriction base="xs:string">
                    <xs:maxLength value="2" />
                  </xs:restriction>
                </xs:simpleType>
              </xs:element>
              <xs:element name="invoiceeOrgId" minOccurs="0">
                <xs:simpleType>
                  <xs:restriction base="xs:string">
                    <xs:maxLength value="4" />
                  </xs:restriction>
                </xs:simpleType>
              </xs:element>
              <xs:element name="invoiceeName">
                <xs:simpleType>
                  <xs:restriction base="xs:string">
                    <xs:maxLength value="70" />
                  </xs:restriction>
                </xs:simpleType>
              </xs:element>
              <xs:element name="invoiceePerson">
                <xs:simpleType>
                  <xs:restriction base="xs:string">
                    <xs:maxLength value="30" />
                  </xs:restriction>
                </xs:simpleType>
              </xs:element>
              <xs:element name="invoiceeAddress" minOccurs="0">
                <xs:simpleType>
                  <xs:restriction base="xs:string">
                    <xs:maxLength value="150" />
                  </xs:restriction>
                </xs:simpleType>
              </xs:element>
              <xs:element name="invoiceeType" minOccurs="0">
                <xs:simpleType>
                  <xs:restriction base="xs:string">
                    <xs:maxLength value="40" />
                  </xs:restriction>
                </xs:simpleType>
              </xs:element>
              <xs:element name="invoiceeClass" minOccurs="0">
                <xs:simpleType>
                  <xs:restriction base="xs:string">
                    <xs:maxLength value="40" />
                  </xs:restriction>
                </xs:simpleType>
              </xs:element>
              <xs:element name="invoiceeDepartment1" minOccurs="0">
                <xs:simpleType>
                  <xs:restriction base="xs:string">
                    <xs:maxLength value="40" />
                  </xs:restriction>
                </xs:simpleType>
              </xs:element>
              <xs:element name="invoiceeContactor1" minOccurs="0">
                <xs:simpleType>
                  <xs:restriction base="xs:string">
                    <xs:maxLength value="30" />
                  </xs:restriction>
                </xs:simpleType>
              </xs:element>
              <xs:element name="invoiceePhone1" minOccurs="0">
                <xs:simpleType>
                  <xs:restriction base="xs:string">
                    <xs:maxLength value="20" />
                  </xs:restriction>
                </xs:simpleType>
              </xs:element>
              <xs:element name="invoiceeEMail1" minOccurs="0">
                <xs:simpleType>
                  <xs:restriction base="xs:string">
                    <xs:maxLength value="40" />
                  </xs:restriction>
                </xs:simpleType>
              </xs:element>
              <xs:element name="invoiceeDepartment2" minOccurs="0">
                <xs:simpleType>
                  <xs:restriction base="xs:string">
                    <xs:maxLength value="40" />
                  </xs:restriction>
                </xs:simpleType>
              </xs:element>
              <xs:element name="invoiceeContactor2" minOccurs="0">
                <xs:simpleType>
                  <xs:restriction base="xs:string">
                    <xs:maxLength value="30" />
                  </xs:restriction>
                </xs:simpleType>
              </xs:element>
              <xs:element name="invoiceePhone2" minOccurs="0">
                <xs:simpleType>
                  <xs:restriction base="xs:string">
                    <xs:maxLength value="20" />
                  </xs:restriction>
                </xs:simpleType>
              </xs:element>
              <xs:element name="invoiceeEMail2" minOccurs="0">
                <xs:simpleType>
                  <xs:restriction base="xs:string">
                    <xs:maxLength value="40" />
                  </xs:restriction>
                </xs:simpleType>
              </xs:element>
              <xs:element name="brokerId" minOccurs="0">
                <xs:simpleType>
                  <xs:restriction base="xs:string">
                    <xs:maxLength value="13" />
                  </xs:restriction>
                </xs:simpleType>
              </xs:element>
              <xs:element name="brokerOrgId" minOccurs="0">
                <xs:simpleType>
                  <xs:restriction base="xs:string">
                    <xs:maxLength value="4" />
                  </xs:restriction>
                </xs:simpleType>
              </xs:element>
              <xs:element name="brokerName" minOccurs="0">
                <xs:simpleType>
                  <xs:restriction base="xs:string">
                    <xs:maxLength value="70" />
                  </xs:restriction>
                </xs:simpleType>
              </xs:element>
              <xs:element name="brokerPerson" minOccurs="0">
                <xs:simpleType>
                  <xs:restriction base="xs:string">
                    <xs:maxLength value="30" />
                  </xs:restriction>
                </xs:simpleType>
              </xs:element>
              <xs:element name="brokerAddress" minOccurs="0">
                <xs:simpleType>
                  <xs:restriction base="xs:string">
                    <xs:maxLength value="150" />
                  </xs:restriction>
                </xs:simpleType>
              </xs:element>
              <xs:element name="brokerType" minOccurs="0">
                <xs:simpleType>
                  <xs:restriction base="xs:string">
                    <xs:maxLength value="40" />
                  </xs:restriction>
                </xs:simpleType>
              </xs:element>
              <xs:element name="brokerClass" minOccurs="0">
                <xs:simpleType>
                  <xs:restriction base="xs:string">
                    <xs:maxLength value="40" />
                  </xs:restriction>
                </xs:simpleType>
              </xs:element>
              <xs:element name="brokerDepartment" minOccurs="0">
                <xs:simpleType>
                  <xs:restriction base="xs:string">
                    <xs:maxLength value="40" />
                  </xs:restriction>
                </xs:simpleType>
              </xs:element>
              <xs:element name="brokerContactor" minOccurs="0">
                <xs:simpleType>
                  <xs:restriction base="xs:string">
                    <xs:maxLength value="30" />
                  </xs:restriction>
                </xs:simpleType>
              </xs:element>
              <xs:element name="brokerPhone" minOccurs="0">
                <xs:simpleType>
                  <xs:restriction base="xs:string">
                    <xs:maxLength value="20" />
                  </xs:restriction>
                </xs:simpleType>
              </xs:element>
              <xs:element name="brokerEMail" minOccurs="0">
                <xs:simpleType>
                  <xs:restriction base="xs:string">
                    <xs:maxLength value="40" />
                  </xs:restriction>
                </xs:simpleType>
              </xs:element>
              <xs:element name="isUploaded">
                <xs:simpleType>
                  <xs:restriction base="xs:string">
                    <xs:maxLength value="1" />
                  </xs:restriction>
                </xs:simpleType>
              </xs:element>
              <xs:element name="paidCash" type="xs:decimal" />
              <xs:element name="paidCheck" type="xs:decimal" />
              <xs:element name="paidNote" type="xs:decimal" />
              <xs:element name="paidCredit" type="xs:decimal" />
              <xs:element name="chargeTotal" type="xs:decimal" />
              <xs:element name="taxTotal" type="xs:decimal" />
              <xs:element name="grandTotal" type="xs:decimal" />
            </xs:sequence>
          </xs:complexType>
        </xs:element>
        <xs:element name="TB_eTAX_LINEITEM">
          <xs:complexType>
            <xs:sequence>
              <xs:element name="issueId">
                <xs:simpleType>
                  <xs:restriction base="xs:string">
                    <xs:maxLength value="24" />
                  </xs:restriction>
                </xs:simpleType>
              </xs:element>
              <xs:element name="seqNo" type="xs:decimal" />
              <xs:element name="purchaseDate" type="xs:dateTime" minOccurs="0" />
              <xs:element name="itemName" minOccurs="0">
                <xs:simpleType>
                  <xs:restriction base="xs:string">
                    <xs:maxLength value="100" />
                  </xs:restriction>
                </xs:simpleType>
              </xs:element>
              <xs:element name="information" minOccurs="0">
                <xs:simpleType>
                  <xs:restriction base="xs:string">
                    <xs:maxLength value="60" />
                  </xs:restriction>
                </xs:simpleType>
              </xs:element>
              <xs:element name="description" minOccurs="0">
                <xs:simpleType>
                  <xs:restriction base="xs:string">
                    <xs:maxLength value="100" />
                  </xs:restriction>
                </xs:simpleType>
              </xs:element>
              <xs:element name="quantity" type="xs:decimal" />
              <xs:element name="unit" minOccurs="0">
                <xs:simpleType>
                  <xs:restriction base="xs:string">
                    <xs:maxLength value="16" />
                  </xs:restriction>
                </xs:simpleType>
              </xs:element>
              <xs:element name="unitPrice" type="xs:decimal" />
              <xs:element name="invoiceAmount" type="xs:decimal" />
              <xs:element name="taxAmount" type="xs:decimal" />
            </xs:sequence>
          </xs:complexType>
        </xs:element>
        <xs:element name="TB_eTAX_RESPONSE">
          <xs:complexType>
            <xs:sequence>
              <xs:element name="submitId">
                <xs:simpleType>
                  <xs:restriction base="xs:string">
                    <xs:maxLength value="50" />
                  </xs:restriction>
                </xs:simpleType>
              </xs:element>
              <xs:element name="typeCode">
                <xs:simpleType>
                  <xs:restriction base="xs:string">
                    <xs:maxLength value="2" />
                  </xs:restriction>
                </xs:simpleType>
              </xs:element>
              <xs:element name="receiptId">
                <xs:simpleType>
                  <xs:restriction base="xs:string">
                    <xs:maxLength value="24" />
                  </xs:restriction>
                </xs:simpleType>
              </xs:element>
              <xs:element name="responseTime" type="xs:dateTime" />
              <xs:element name="processStatus" minOccurs="0">
                <xs:simpleType>
                  <xs:restriction base="xs:string">
                    <xs:maxLength value="2" />
                  </xs:restriction>
                </xs:simpleType>
              </xs:element>
              <xs:element name="failReason" minOccurs="0">
                <xs:simpleType>
                  <xs:restriction base="xs:string">
                    <xs:maxLength value="6" />
                  </xs:restriction>
                </xs:simpleType>
              </xs:element>
              <xs:element name="totalCount" type="xs:decimal" />
              <xs:element name="successCount" type="xs:decimal" />
              <xs:element name="failCount" type="xs:decimal" />
            </xs:sequence>
          </xs:complexType>
        </xs:element>
        <xs:element name="TB_eTAX_RESULT">
          <xs:complexType>
            <xs:sequence>
              <xs:element name="issueId">
                <xs:simpleType>
                  <xs:restriction base="xs:string">
                    <xs:maxLength value="24" />
                  </xs:restriction>
                </xs:simpleType>
              </xs:element>
              <xs:element name="resultStatus">
                <xs:simpleType>
                  <xs:restriction base="xs:string">
                    <xs:maxLength value="6" />
                  </xs:restriction>
                </xs:simpleType>
              </xs:element>
              <xs:element name="isDone">
                <xs:simpleType>
                  <xs:restriction base="xs:string">
                    <xs:maxLength value="1" />
                  </xs:restriction>
                </xs:simpleType>
              </xs:element>
              <xs:element name="message" minOccurs="0">
                <xs:simpleType>
                  <xs:restriction base="xs:string">
                    <xs:maxLength value="1024" />
                  </xs:restriction>
                </xs:simpleType>
              </xs:element>
              <xs:element name="created" type="xs:dateTime" />
            </xs:sequence>
          </xs:complexType>
        </xs:element>
        <xs:element name="TB_eTAX_PURCHASE">
          <xs:complexType>
            <xs:sequence>
              <xs:element name="exchangeId">
                <xs:simpleType>
                  <xs:restriction base="xs:string">
                    <xs:maxLength value="24" />
                  </xs:restriction>
                </xs:simpleType>
              </xs:element>
              <xs:element name="exchangeDate" type="xs:dateTime" minOccurs="0" />
              <xs:element name="creator" minOccurs="0">
                <xs:simpleType>
                  <xs:restriction base="xs:string">
                    <xs:maxLength value="30" />
                  </xs:restriction>
                </xs:simpleType>
              </xs:element>
              <xs:element name="issueId">
                <xs:simpleType>
                  <xs:restriction base="xs:string">
                    <xs:maxLength value="24" />
                  </xs:restriction>
                </xs:simpleType>
              </xs:element>
              <xs:element name="issueDate" type="xs:dateTime" />
              <xs:element name="typeCode">
                <xs:simpleType>
                  <xs:restriction base="xs:string">
                    <xs:maxLength value="4" />
                  </xs:restriction>
                </xs:simpleType>
              </xs:element>
              <xs:element name="purposeCode" minOccurs="0">
                <xs:simpleType>
                  <xs:restriction base="xs:string">
                    <xs:maxLength value="2" />
                  </xs:restriction>
                </xs:simpleType>
              </xs:element>
              <xs:element name="amendmentCode" minOccurs="0">
                <xs:simpleType>
                  <xs:restriction base="xs:string">
                    <xs:maxLength value="2" />
                  </xs:restriction>
                </xs:simpleType>
              </xs:element>
              <xs:element name="description" minOccurs="0">
                <xs:simpleType>
                  <xs:restriction base="xs:string">
                    <xs:maxLength value="150" />
                  </xs:restriction>
                </xs:simpleType>
              </xs:element>
              <xs:element name="importId" minOccurs="0">
                <xs:simpleType>
                  <xs:restriction base="xs:string">
                    <xs:maxLength value="15" />
                  </xs:restriction>
                </xs:simpleType>
              </xs:element>
              <xs:element name="importStart" type="xs:dateTime" minOccurs="0" />
              <xs:element name="importEnd" type="xs:dateTime" minOccurs="0" />
              <xs:element name="importQuantity" type="xs:decimal" />
              <xs:element name="invoicerId">
                <xs:simpleType>
                  <xs:restriction base="xs:string">
                    <xs:maxLength value="13" />
                  </xs:restriction>
                </xs:simpleType>
              </xs:element>
              <xs:element name="invoicerOrgId" minOccurs="0">
                <xs:simpleType>
                  <xs:restriction base="xs:string">
                    <xs:maxLength value="4" />
                  </xs:restriction>
                </xs:simpleType>
              </xs:element>
              <xs:element name="invoicerName">
                <xs:simpleType>
                  <xs:restriction base="xs:string">
                    <xs:maxLength value="70" />
                  </xs:restriction>
                </xs:simpleType>
              </xs:element>
              <xs:element name="invoicerPerson">
                <xs:simpleType>
                  <xs:restriction base="xs:string">
                    <xs:maxLength value="30" />
                  </xs:restriction>
                </xs:simpleType>
              </xs:element>
              <xs:element name="invoicerAddress" minOccurs="0">
                <xs:simpleType>
                  <xs:restriction base="xs:string">
                    <xs:maxLength value="150" />
                  </xs:restriction>
                </xs:simpleType>
              </xs:element>
              <xs:element name="invoicerType" minOccurs="0">
                <xs:simpleType>
                  <xs:restriction base="xs:string">
                    <xs:maxLength value="40" />
                  </xs:restriction>
                </xs:simpleType>
              </xs:element>
              <xs:element name="invoicerClass" minOccurs="0">
                <xs:simpleType>
                  <xs:restriction base="xs:string">
                    <xs:maxLength value="40" />
                  </xs:restriction>
                </xs:simpleType>
              </xs:element>
              <xs:element name="invoicerDepartment" minOccurs="0">
                <xs:simpleType>
                  <xs:restriction base="xs:string">
                    <xs:maxLength value="40" />
                  </xs:restriction>
                </xs:simpleType>
              </xs:element>
              <xs:element name="invoicerContactor" minOccurs="0">
                <xs:simpleType>
                  <xs:restriction base="xs:string">
                    <xs:maxLength value="30" />
                  </xs:restriction>
                </xs:simpleType>
              </xs:element>
              <xs:element name="invoicerPhone" minOccurs="0">
                <xs:simpleType>
                  <xs:restriction base="xs:string">
                    <xs:maxLength value="20" />
                  </xs:restriction>
                </xs:simpleType>
              </xs:element>
              <xs:element name="invoicerEMail" minOccurs="0">
                <xs:simpleType>
                  <xs:restriction base="xs:string">
                    <xs:maxLength value="40" />
                  </xs:restriction>
                </xs:simpleType>
              </xs:element>
              <xs:element name="invoiceeId">
                <xs:simpleType>
                  <xs:restriction base="xs:string">
                    <xs:maxLength value="13" />
                  </xs:restriction>
                </xs:simpleType>
              </xs:element>
              <xs:element name="invoiceeKind">
                <xs:simpleType>
                  <xs:restriction base="xs:string">
                    <xs:maxLength value="2" />
                  </xs:restriction>
                </xs:simpleType>
              </xs:element>
              <xs:element name="invoiceeOrgId" minOccurs="0">
                <xs:simpleType>
                  <xs:restriction base="xs:string">
                    <xs:maxLength value="4" />
                  </xs:restriction>
                </xs:simpleType>
              </xs:element>
              <xs:element name="invoiceeName">
                <xs:simpleType>
                  <xs:restriction base="xs:string">
                    <xs:maxLength value="70" />
                  </xs:restriction>
                </xs:simpleType>
              </xs:element>
              <xs:element name="invoiceePerson">
                <xs:simpleType>
                  <xs:restriction base="xs:string">
                    <xs:maxLength value="30" />
                  </xs:restriction>
                </xs:simpleType>
              </xs:element>
              <xs:element name="invoiceeAddress" minOccurs="0">
                <xs:simpleType>
                  <xs:restriction base="xs:string">
                    <xs:maxLength value="150" />
                  </xs:restriction>
                </xs:simpleType>
              </xs:element>
              <xs:element name="invoiceeType" minOccurs="0">
                <xs:simpleType>
                  <xs:restriction base="xs:string">
                    <xs:maxLength value="40" />
                  </xs:restriction>
                </xs:simpleType>
              </xs:element>
              <xs:element name="invoiceeClass" minOccurs="0">
                <xs:simpleType>
                  <xs:restriction base="xs:string">
                    <xs:maxLength value="40" />
                  </xs:restriction>
                </xs:simpleType>
              </xs:element>
              <xs:element name="invoiceeDepartment1" minOccurs="0">
                <xs:simpleType>
                  <xs:restriction base="xs:string">
                    <xs:maxLength value="40" />
                  </xs:restriction>
                </xs:simpleType>
              </xs:element>
              <xs:element name="invoiceeContactor1" minOccurs="0">
                <xs:simpleType>
                  <xs:restriction base="xs:string">
                    <xs:maxLength value="30" />
                  </xs:restriction>
                </xs:simpleType>
              </xs:element>
              <xs:element name="invoiceePhone1" minOccurs="0">
                <xs:simpleType>
                  <xs:restriction base="xs:string">
                    <xs:maxLength value="20" />
                  </xs:restriction>
                </xs:simpleType>
              </xs:element>
              <xs:element name="invoiceeEMail1" minOccurs="0">
                <xs:simpleType>
                  <xs:restriction base="xs:string">
                    <xs:maxLength value="40" />
                  </xs:restriction>
                </xs:simpleType>
              </xs:element>
              <xs:element name="invoiceeDepartment2" minOccurs="0">
                <xs:simpleType>
                  <xs:restriction base="xs:string">
                    <xs:maxLength value="40" />
                  </xs:restriction>
                </xs:simpleType>
              </xs:element>
              <xs:element name="invoiceeContactor2" minOccurs="0">
                <xs:simpleType>
                  <xs:restriction base="xs:string">
                    <xs:maxLength value="30" />
                  </xs:restriction>
                </xs:simpleType>
              </xs:element>
              <xs:element name="invoiceePhone2" minOccurs="0">
                <xs:simpleType>
                  <xs:restriction base="xs:string">
                    <xs:maxLength value="20" />
                  </xs:restriction>
                </xs:simpleType>
              </xs:element>
              <xs:element name="invoiceeEMail2" minOccurs="0">
                <xs:simpleType>
                  <xs:restriction base="xs:string">
                    <xs:maxLength value="40" />
                  </xs:restriction>
                </xs:simpleType>
              </xs:element>
              <xs:element name="brokerId" minOccurs="0">
                <xs:simpleType>
                  <xs:restriction base="xs:string">
                    <xs:maxLength value="13" />
                  </xs:restriction>
                </xs:simpleType>
              </xs:element>
              <xs:element name="brokerOrgId" minOccurs="0">
                <xs:simpleType>
                  <xs:restriction base="xs:string">
                    <xs:maxLength value="4" />
                  </xs:restriction>
                </xs:simpleType>
              </xs:element>
              <xs:element name="brokerName" minOccurs="0">
                <xs:simpleType>
                  <xs:restriction base="xs:string">
                    <xs:maxLength value="70" />
                  </xs:restriction>
                </xs:simpleType>
              </xs:element>
              <xs:element name="brokerPerson" minOccurs="0">
                <xs:simpleType>
                  <xs:restriction base="xs:string">
                    <xs:maxLength value="30" />
                  </xs:restriction>
                </xs:simpleType>
              </xs:element>
              <xs:element name="brokerAddress" minOccurs="0">
                <xs:simpleType>
                  <xs:restriction base="xs:string">
                    <xs:maxLength value="150" />
                  </xs:restriction>
                </xs:simpleType>
              </xs:element>
              <xs:element name="brokerType" minOccurs="0">
                <xs:simpleType>
                  <xs:restriction base="xs:string">
                    <xs:maxLength value="40" />
                  </xs:restriction>
                </xs:simpleType>
              </xs:element>
              <xs:element name="brokerClass" minOccurs="0">
                <xs:simpleType>
                  <xs:restriction base="xs:string">
                    <xs:maxLength value="40" />
                  </xs:restriction>
                </xs:simpleType>
              </xs:element>
              <xs:element name="brokerDepartment" minOccurs="0">
                <xs:simpleType>
                  <xs:restriction base="xs:string">
                    <xs:maxLength value="40" />
                  </xs:restriction>
                </xs:simpleType>
              </xs:element>
              <xs:element name="brokerContactor" minOccurs="0">
                <xs:simpleType>
                  <xs:restriction base="xs:string">
                    <xs:maxLength value="30" />
                  </xs:restriction>
                </xs:simpleType>
              </xs:element>
              <xs:element name="brokerPhone" minOccurs="0">
                <xs:simpleType>
                  <xs:restriction base="xs:string">
                    <xs:maxLength value="20" />
                  </xs:restriction>
                </xs:simpleType>
              </xs:element>
              <xs:element name="brokerEMail" minOccurs="0">
                <xs:simpleType>
                  <xs:restriction base="xs:string">
                    <xs:maxLength value="40" />
                  </xs:restriction>
                </xs:simpleType>
              </xs:element>
              <xs:element name="paidCash" type="xs:decimal" />
              <xs:element name="paidCheck" type="xs:decimal" />
              <xs:element name="paidNote" type="xs:decimal" />
              <xs:element name="paidCredit" type="xs:decimal" />
              <xs:element name="chargeTotal" type="xs:decimal" />
              <xs:element name="taxTotal" type="xs:decimal" />
              <xs:element name="grandTotal" type="xs:decimal" />
            </xs:sequence>
          </xs:complexType>
        </xs:element>
        <xs:element name="TB_eTAX_PURITEM">
          <xs:complexType>
            <xs:sequence>
              <xs:element name="issueId">
                <xs:simpleType>
                  <xs:restriction base="xs:string">
                    <xs:maxLength value="24" />
                  </xs:restriction>
                </xs:simpleType>
              </xs:element>
              <xs:element name="seqNo" type="xs:decimal" />
              <xs:element name="purchaseDate" type="xs:dateTime" minOccurs="0" />
              <xs:element name="itemName" minOccurs="0">
                <xs:simpleType>
                  <xs:restriction base="xs:string">
                    <xs:maxLength value="100" />
                  </xs:restriction>
                </xs:simpleType>
              </xs:element>
              <xs:element name="information" minOccurs="0">
                <xs:simpleType>
                  <xs:restriction base="xs:string">
                    <xs:maxLength value="60" />
                  </xs:restriction>
                </xs:simpleType>
              </xs:element>
              <xs:element name="description" minOccurs="0">
                <xs:simpleType>
                  <xs:restriction base="xs:string">
                    <xs:maxLength value="100" />
                  </xs:restriction>
                </xs:simpleType>
              </xs:element>
              <xs:element name="quantity" type="xs:decimal" />
              <xs:element name="unit" minOccurs="0">
                <xs:simpleType>
                  <xs:restriction base="xs:string">
                    <xs:maxLength value="16" />
                  </xs:restriction>
                </xs:simpleType>
              </xs:element>
              <xs:element name="unitPrice" type="xs:decimal" />
              <xs:element name="invoiceAmount" type="xs:decimal" />
              <xs:element name="taxAmount" type="xs:decimal" />
            </xs:sequence>
          </xs:complexType>
        </xs:element>
        <xs:element name="TB_eTAX_ISSUING">
          <xs:complexType>
            <xs:sequence>
              <xs:element name="issueId">
                <xs:simpleType>
                  <xs:restriction base="xs:string">
                    <xs:maxLength value="24" />
                  </xs:restriction>
                </xs:simpleType>
              </xs:element>
              <xs:element name="document">
                <xs:simpleType>
                  <xs:restriction base="xs:string">
                    <xs:maxLength value="2147483647" />
                  </xs:restriction>
                </xs:simpleType>
              </xs:element>
              <xs:element name="rvalue">
                <xs:simpleType>
                  <xs:restriction base="xs:string">
                    <xs:maxLength value="64" />
                  </xs:restriction>
                </xs:simpleType>
              </xs:element>
              <xs:element name="signingDate" type="xs:dateTime" />
              <xs:element name="securityId" minOccurs="0">
                <xs:simpleType>
                  <xs:restriction base="xs:string">
                    <xs:maxLength value="6" />
                  </xs:restriction>
                </xs:simpleType>
              </xs:element>
              <xs:element name="sendMailCount" type="xs:decimal" />
              <xs:element name="isMailSending">
                <xs:simpleType>
                  <xs:restriction base="xs:string">
                    <xs:maxLength value="1" />
                  </xs:restriction>
                </xs:simpleType>
              </xs:element>
              <xs:element name="mailSendingDate" type="xs:dateTime" minOccurs="0" />
              <xs:element name="isInvoiceeMail">
                <xs:simpleType>
                  <xs:restriction base="xs:string">
                    <xs:maxLength value="1" />
                  </xs:restriction>
                </xs:simpleType>
              </xs:element>
              <xs:element name="isProviderMail">
                <xs:simpleType>
                  <xs:restriction base="xs:string">
                    <xs:maxLength value="1" />
                  </xs:restriction>
                </xs:simpleType>
              </xs:element>
              <xs:element name="providerId" minOccurs="0">
                <xs:simpleType>
                  <xs:restriction base="xs:string">
                    <xs:maxLength value="13" />
                  </xs:restriction>
                </xs:simpleType>
              </xs:element>
              <xs:element name="providerEMail" minOccurs="0">
                <xs:simpleType>
                  <xs:restriction base="xs:string">
                    <xs:maxLength value="40" />
                  </xs:restriction>
                </xs:simpleType>
              </xs:element>
              <xs:element name="isBuyerConfirm">
                <xs:simpleType>
                  <xs:restriction base="xs:string">
                    <xs:maxLength value="1" />
                  </xs:restriction>
                </xs:simpleType>
              </xs:element>
              <xs:element name="buyerConfirmDate" type="xs:dateTime" minOccurs="0" />
              <xs:element name="isNTSSending">
                <xs:simpleType>
                  <xs:restriction base="xs:string">
                    <xs:maxLength value="1" />
                  </xs:restriction>
                </xs:simpleType>
              </xs:element>
              <xs:element name="isNTSReport">
                <xs:simpleType>
                  <xs:restriction base="xs:string">
                    <xs:maxLength value="1" />
                  </xs:restriction>
                </xs:simpleType>
              </xs:element>
              <xs:element name="ntsReportingDate" type="xs:dateTime" minOccurs="0" />
              <xs:element name="isNTSConfirm">
                <xs:simpleType>
                  <xs:restriction base="xs:string">
                    <xs:maxLength value="1" />
                  </xs:restriction>
                </xs:simpleType>
              </xs:element>
              <xs:element name="ntsConfirmDate" type="xs:dateTime" minOccurs="0" />
              <xs:element name="isNTSSuccess">
                <xs:simpleType>
                  <xs:restriction base="xs:string">
                    <xs:maxLength value="1" />
                  </xs:restriction>
                </xs:simpleType>
              </xs:element>
              <xs:element name="submitId" minOccurs="0">
                <xs:simpleType>
                  <xs:restriction base="xs:string">
                    <xs:maxLength value="50" />
                  </xs:restriction>
                </xs:simpleType>
              </xs:element>
            </xs:sequence>
          </xs:complexType>
        </xs:element>
        <xs:element name="TB_eTAX_CUSTOMER">
          <xs:complexType>
            <xs:sequence>
              <xs:element name="customerId">
                <xs:simpleType>
                  <xs:restriction base="xs:string">
                    <xs:maxLength value="13" />
                  </xs:restriction>
                </xs:simpleType>
              </xs:element>
              <xs:element name="kind">
                <xs:simpleType>
                  <xs:restriction base="xs:string">
                    <xs:maxLength value="2" />
                  </xs:restriction>
                </xs:simpleType>
              </xs:element>
              <xs:element name="openDate" type="xs:dateTime" minOccurs="0" />
              <xs:element name="issueDate" type="xs:dateTime" minOccurs="0" />
              <xs:element name="legalId" minOccurs="0">
                <xs:simpleType>
                  <xs:restriction base="xs:string">
                    <xs:maxLength value="13" />
                  </xs:restriction>
                </xs:simpleType>
              </xs:element>
              <xs:element name="taxOffice" minOccurs="0">
                <xs:simpleType>
                  <xs:restriction base="xs:string">
                    <xs:maxLength value="70" />
                  </xs:restriction>
                </xs:simpleType>
              </xs:element>
              <xs:element name="name">
                <xs:simpleType>
                  <xs:restriction base="xs:string">
                    <xs:maxLength value="70" />
                  </xs:restriction>
                </xs:simpleType>
              </xs:element>
              <xs:element name="person">
                <xs:simpleType>
                  <xs:restriction base="xs:string">
                    <xs:maxLength value="30" />
                  </xs:restriction>
                </xs:simpleType>
              </xs:element>
              <xs:element name="address" minOccurs="0">
                <xs:simpleType>
                  <xs:restriction base="xs:string">
                    <xs:maxLength value="150" />
                  </xs:restriction>
                </xs:simpleType>
              </xs:element>
              <xs:element name="type" minOccurs="0">
                <xs:simpleType>
                  <xs:restriction base="xs:string">
                    <xs:maxLength value="40" />
                  </xs:restriction>
                </xs:simpleType>
              </xs:element>
              <xs:element name="class" minOccurs="0">
                <xs:simpleType>
                  <xs:restriction base="xs:string">
                    <xs:maxLength value="40" />
                  </xs:restriction>
                </xs:simpleType>
              </xs:element>
              <xs:element name="department1" minOccurs="0">
                <xs:simpleType>
                  <xs:restriction base="xs:string">
                    <xs:maxLength value="40" />
                  </xs:restriction>
                </xs:simpleType>
              </xs:element>
              <xs:element name="contactor1" minOccurs="0">
                <xs:simpleType>
                  <xs:restriction base="xs:string">
                    <xs:maxLength value="30" />
                  </xs:restriction>
                </xs:simpleType>
              </xs:element>
              <xs:element name="phone1" minOccurs="0">
                <xs:simpleType>
                  <xs:restriction base="xs:string">
                    <xs:maxLength value="20" />
                  </xs:restriction>
                </xs:simpleType>
              </xs:element>
              <xs:element name="eMail1" minOccurs="0">
                <xs:simpleType>
                  <xs:restriction base="xs:string">
                    <xs:maxLength value="40" />
                  </xs:restriction>
                </xs:simpleType>
              </xs:element>
              <xs:element name="department2" minOccurs="0">
                <xs:simpleType>
                  <xs:restriction base="xs:string">
                    <xs:maxLength value="40" />
                  </xs:restriction>
                </xs:simpleType>
              </xs:element>
              <xs:element name="contactor2" minOccurs="0">
                <xs:simpleType>
                  <xs:restriction base="xs:string">
                    <xs:maxLength value="30" />
                  </xs:restriction>
                </xs:simpleType>
              </xs:element>
              <xs:element name="phone2" minOccurs="0">
                <xs:simpleType>
                  <xs:restriction base="xs:string">
                    <xs:maxLength value="20" />
                  </xs:restriction>
                </xs:simpleType>
              </xs:element>
              <xs:element name="eMail2" minOccurs="0">
                <xs:simpleType>
                  <xs:restriction base="xs:string">
                    <xs:maxLength value="40" />
                  </xs:restriction>
                </xs:simpleType>
              </xs:element>
              <xs:element name="bizregCopy" type="xs:base64Binary" minOccurs="0" />
              <xs:element name="bizregAttach">
                <xs:simpleType>
                  <xs:restriction base="xs:string">
                    <xs:maxLength value="1" />
                  </xs:restriction>
                </xs:simpleType>
              </xs:element>
              <xs:element name="bankbookCopy" type="xs:base64Binary" minOccurs="0" />
              <xs:element name="bankbookAttach">
                <xs:simpleType>
                  <xs:restriction base="xs:string">
                    <xs:maxLength value="1" />
                  </xs:restriction>
                </xs:simpleType>
              </xs:element>
              <xs:element name="providerId" minOccurs="0">
                <xs:simpleType>
                  <xs:restriction base="xs:string">
                    <xs:maxLength value="13" />
                  </xs:restriction>
                </xs:simpleType>
              </xs:element>
              <xs:element name="headOffice" minOccurs="0">
                <xs:simpleType>
                  <xs:restriction base="xs:string">
                    <xs:maxLength value="13" />
                  </xs:restriction>
                </xs:simpleType>
              </xs:element>
              <xs:element name="taxRegId" minOccurs="0">
                <xs:simpleType>
                  <xs:restriction base="xs:string">
                    <xs:maxLength value="4" />
                  </xs:restriction>
                </xs:simpleType>
              </xs:element>
              <xs:element name="publicKey" minOccurs="0">
                <xs:simpleType>
                  <xs:restriction base="xs:string">
                    <xs:maxLength value="2147483647" />
                  </xs:restriction>
                </xs:simpleType>
              </xs:element>
              <xs:element name="privateKey" minOccurs="0">
                <xs:simpleType>
                  <xs:restriction base="xs:string">
                    <xs:maxLength value="2147483647" />
                  </xs:restriction>
                </xs:simpleType>
              </xs:element>
              <xs:element name="password" minOccurs="0">
                <xs:simpleType>
                  <xs:restriction base="xs:string">
                    <xs:maxLength value="2147483647" />
                  </xs:restriction>
                </xs:simpleType>
              </xs:element>
              <xs:element name="expiration" type="xs:dateTime" minOccurs="0" />
              <xs:element name="closingDay" type="xs:decimal" />
              <xs:element name="signingType">
                <xs:simpleType>
                  <xs:restriction base="xs:string">
                    <xs:maxLength value="2" />
                  </xs:restriction>
                </xs:simpleType>
              </xs:element>
              <xs:element name="signFromDay" type="xs:decimal" />
              <xs:element name="signTillDay" type="xs:decimal" />
              <xs:element name="sendingType">
                <xs:simpleType>
                  <xs:restriction base="xs:string">
                    <xs:maxLength value="2" />
                  </xs:restriction>
                </xs:simpleType>
              </xs:element>
              <xs:element name="sendFromDay" type="xs:decimal" />
              <xs:element name="sendTillDay" type="xs:decimal" />
              <xs:element name="reportingType">
                <xs:simpleType>
                  <xs:restriction base="xs:string">
                    <xs:maxLength value="2" />
                  </xs:restriction>
                </xs:simpleType>
              </xs:element>
              <xs:element name="reportFromDay" type="xs:decimal" />
              <xs:element name="reportTillDay" type="xs:decimal" />
              <xs:element name="reportCondition">
                <xs:simpleType>
                  <xs:restriction base="xs:string">
                    <xs:maxLength value="2" />
                  </xs:restriction>
                </xs:simpleType>
              </xs:element>
            </xs:sequence>
          </xs:complexType>
        </xs:element>
        <xs:element name="TB_eTAX_PARTNER">
          <xs:complexType>
            <xs:sequence>
              <xs:element name="userId">
                <xs:simpleType>
                  <xs:restriction base="xs:string">
                    <xs:maxLength value="30" />
                  </xs:restriction>
                </xs:simpleType>
              </xs:element>
              <xs:element name="customerId">
                <xs:simpleType>
                  <xs:restriction base="xs:string">
                    <xs:maxLength value="13" />
                  </xs:restriction>
                </xs:simpleType>
              </xs:element>
              <xs:element name="name">
                <xs:simpleType>
                  <xs:restriction base="xs:string">
                    <xs:maxLength value="70" />
                  </xs:restriction>
                </xs:simpleType>
              </xs:element>
              <xs:element name="person">
                <xs:simpleType>
                  <xs:restriction base="xs:string">
                    <xs:maxLength value="30" />
                  </xs:restriction>
                </xs:simpleType>
              </xs:element>
              <xs:element name="address" minOccurs="0">
                <xs:simpleType>
                  <xs:restriction base="xs:string">
                    <xs:maxLength value="150" />
                  </xs:restriction>
                </xs:simpleType>
              </xs:element>
              <xs:element name="type" minOccurs="0">
                <xs:simpleType>
                  <xs:restriction base="xs:string">
                    <xs:maxLength value="40" />
                  </xs:restriction>
                </xs:simpleType>
              </xs:element>
              <xs:element name="class" minOccurs="0">
                <xs:simpleType>
                  <xs:restriction base="xs:string">
                    <xs:maxLength value="40" />
                  </xs:restriction>
                </xs:simpleType>
              </xs:element>
              <xs:element name="department1" minOccurs="0">
                <xs:simpleType>
                  <xs:restriction base="xs:string">
                    <xs:maxLength value="40" />
                  </xs:restriction>
                </xs:simpleType>
              </xs:element>
              <xs:element name="contactor1" minOccurs="0">
                <xs:simpleType>
                  <xs:restriction base="xs:string">
                    <xs:maxLength value="30" />
                  </xs:restriction>
                </xs:simpleType>
              </xs:element>
              <xs:element name="phone1" minOccurs="0">
                <xs:simpleType>
                  <xs:restriction base="xs:string">
                    <xs:maxLength value="20" />
                  </xs:restriction>
                </xs:simpleType>
              </xs:element>
              <xs:element name="eMail1" minOccurs="0">
                <xs:simpleType>
                  <xs:restriction base="xs:string">
                    <xs:maxLength value="40" />
                  </xs:restriction>
                </xs:simpleType>
              </xs:element>
              <xs:element name="department2" minOccurs="0">
                <xs:simpleType>
                  <xs:restriction base="xs:string">
                    <xs:maxLength value="40" />
                  </xs:restriction>
                </xs:simpleType>
              </xs:element>
              <xs:element name="contactor2" minOccurs="0">
                <xs:simpleType>
                  <xs:restriction base="xs:string">
                    <xs:maxLength value="30" />
                  </xs:restriction>
                </xs:simpleType>
              </xs:element>
              <xs:element name="phone2" minOccurs="0">
                <xs:simpleType>
                  <xs:restriction base="xs:string">
                    <xs:maxLength value="20" />
                  </xs:restriction>
                </xs:simpleType>
              </xs:element>
              <xs:element name="eMail2" minOccurs="0">
                <xs:simpleType>
                  <xs:restriction base="xs:string">
                    <xs:maxLength value="40" />
                  </xs:restriction>
                </xs:simpleType>
              </xs:element>
            </xs:sequence>
          </xs:complexType>
        </xs:element>
      </xs:choice>
    </xs:complexType>
    <xs:unique name="Constraint1" msdata:PrimaryKey="true">
      <xs:selector xpath=".//TB_eTAX_INVOICE" />
      <xs:field xpath="issueId" />
    </xs:unique>
    <xs:unique name="TB_eTAX_LINEITEM_Constraint1" msdata:ConstraintName="Constraint1" msdata:PrimaryKey="true">
      <xs:selector xpath=".//TB_eTAX_LINEITEM" />
      <xs:field xpath="issueId" />
      <xs:field xpath="seqNo" />
    </xs:unique>
    <xs:unique name="TB_eTAX_RESPONSE_Constraint1" msdata:ConstraintName="Constraint1" msdata:PrimaryKey="true">
      <xs:selector xpath=".//TB_eTAX_RESPONSE" />
      <xs:field xpath="submitId" />
      <xs:field xpath="typeCode" />
    </xs:unique>
    <xs:unique name="TB_eTAX_RESULT_Constraint1" msdata:ConstraintName="Constraint1" msdata:PrimaryKey="true">
      <xs:selector xpath=".//TB_eTAX_RESULT" />
      <xs:field xpath="issueId" />
      <xs:field xpath="resultStatus" />
    </xs:unique>
    <xs:unique name="TB_eTAX_PURCHASE_Constraint1" msdata:ConstraintName="Constraint1" msdata:PrimaryKey="true">
      <xs:selector xpath=".//TB_eTAX_PURCHASE" />
      <xs:field xpath="issueId" />
    </xs:unique>
    <xs:unique name="TB_eTAX_PURITEM_Constraint1" msdata:ConstraintName="Constraint1" msdata:PrimaryKey="true">
      <xs:selector xpath=".//TB_eTAX_PURITEM" />
      <xs:field xpath="issueId" />
      <xs:field xpath="seqNo" />
    </xs:unique>
    <xs:unique name="TB_eTAX_ISSUING_Constraint1" msdata:ConstraintName="Constraint1" msdata:PrimaryKey="true">
      <xs:selector xpath=".//TB_eTAX_ISSUING" />
      <xs:field xpath="issueId" />
    </xs:unique>
    <xs:unique name="TB_eTAX_CUSTOMER_Constraint1" msdata:ConstraintName="Constraint1" msdata:PrimaryKey="true">
      <xs:selector xpath=".//TB_eTAX_CUSTOMER" />
      <xs:field xpath="customerId" />
    </xs:unique>
    <xs:unique name="TB_eTAX_PARTNER_Constraint1" msdata:ConstraintName="Constraint1" msdata:PrimaryKey="true">
      <xs:selector xpath=".//TB_eTAX_PARTNER" />
      <xs:field xpath="userId" />
      <xs:field xpath="customerId" />
    </xs:unique>
  </xs:element>
</xs:schema>